tracking_numbers/__init__.py
tracking_numbers/_generated.py
tracking_numbers/checksum_validator.py
tracking_numbers/compat.py
tracking_numbers/definition.py
tracking_numbers/helpers/__init__.py
tracking_numbers/helpers/repr.py
tracking_numbers/helpers/spec.py
tracking_numbers/serial_number.py
tracking_numbers/types.py
tracking_numbers/value_matcher.py
tracking_numbers-0.1.7.dist-info/WHEEL
tracking_numbers-0.1.7.dist-info/METADATA
tracking_numbers-0.1.7.dist-info/RECORD
