Metadata-Version: 2.1
Name: tracking-numbers
Version: 0.1.7
Summary: Parse tracking numbers from couriers with no external dependencies
Home-page: https://github.com/jcomo/tracking-numbers
License: MIT
Keywords: tracking,tracking numbers,courier,shipping
Author: Jonathan Como
Author-email: public@jcomo.me
Requires-Python: >=3.9,<4.0
Classifier: License :: OSI Approved :: MIT License
Classifier: Programming Language :: Python :: 3
Classifier: Programming Language :: Python :: 3.10
Classifier: Programming Language :: Python :: 3.9
Project-URL: Repository, https://github.com/jcomo/tracking-numbers
